[{"id":1,"username":"bennyBlanco","password":"abcdefgh","email":"ben@somesite.com","age":25},{"id":3,"username":"sean","password":"zxcvbnma","email":"sean100@outlook.com","age":60},{"id":4,"username":"doug","password":"qwertyui","email":"doug1000@gmail.com","age":23},{"id":6,"username":"willy","password":"poiuytre","email":"willy@examplesite.com","age":19},{"id":7,"username":"benjiDelomanos","password":"blahblahblah","email":"benji500@gmail.com","age":30},{"id":8,"username":"raymond","password":"mnbvcxza","email":"ray@somesite.com","age":43},{"id":9,"username":"slowJergens","password":"slowjergens","email":"slowjergens@aol.com","age":600},{"id":10,"username":"fatsDomino","password":"fatcats100","email":"fats100@gmail.com","age":80},{"username":"SeanConnery","password":"0000000007","email":"seandog@scotland.uk","age":81,"id":12},{"username":"GaryPowers","password":"garypowers","email":"garyp1000@yahoo.com","age":45,"id":14}]